{"name":"Menyukai postingan pada feed","id":"search-by-keyword;menyukai-postingan-pada-feed","testSteps":[{"number":1,"description":"Given Pengguna berada pada Beranda LinkedIn","duration":1,"startTime":"2022-02-13T09:53:56.289454217Z[Etc/UTC]","result":"SUCCESS","precondition":false,"level":0},{"number":2,"description":"When Pengguna click button suka pada postingan","duration":1,"startTime":"2022-02-13T09:53:56.291649585Z[Etc/UTC]","result":"SUCCESS","precondition":false,"level":0},{"number":3,"description":"Then Button suka akan berwarna biru pada postingan","duration":0,"startTime":"2022-02-13T09:53:56.294093850Z[Etc/UTC]","result":"SUCCESS","precondition":false,"level":0}],"userStory":{"id":"search-by-keyword","storyName":"Search by keyword","displayName":"Search by keyword","path":"search/tugas_bdd_linkedin.feature","type":"feature"},"featureTag":{"name":"Search/Search by keyword","type":"feature","displayName":"Search/Search by keyword"},"title":"Menyukai postingan pada feed","description":"","tags":[{"name":"Search/Search by keyword","type":"feature","displayName":"Search by keyword"},{"name":"all","type":"tag","displayName":"all"},{"name":"Search","type":"capability","displayName":"Search"}],"startTime":"2022-02-13T09:53:56.284155693Z[Etc/UTC]","duration":12,"projectKey":"","isManualTestingUpToDate":false,"manual":false,"testSource":"Cucumber","result":"SUCCESS"}